Metadata-Version: 1.0
Name: gulpy
Version: 0.1
Summary: Gulpy task runner
Home-page: http://gulpy.readthedocs.io/en/latest/
Author: Gilmar Quinelato
Author-email: gilmarsquinelato@gmail.com
License: MIT
Keywords: gulpy task runner build
Platform: UNKNOWN
